documentation/__init__.py
documentation/doc_dao.py
documentation/doc_dto.py
tutorial/__init__.py
tutorial/step_dto.py
tutorial/tut_dto.py
doc_controller-0.0.3.dist-info/LICENSE
doc_controller-0.0.3.dist-info/METADATA
doc_controller-0.0.3.dist-info/WHEEL
doc_controller-0.0.3.dist-info/top_level.txt
doc_controller-0.0.3.dist-info/RECORD
