Metadata-Version: 2.1
Name: doc-controller
Version: 0.0.3
Summary: To update and retrieve documentation data
Author: Bernard Birendra Das
Author-email: <bernardbdas@gmail.com>
Keywords: python,conversational AI,AI,Task Automation,SimplifyQA,Simplify3x
Classifier: Development Status :: 1 - Planning
Classifier: Intended Audience :: Developers
Classifier: Programming Language :: Python :: 3
Classifier: Operating System :: Unix
Classifier: Operating System :: MacOS :: MacOS X
Classifier: Operating System :: Microsoft :: Windows
License-File: LICENSE
Requires-Dist: rasa
